Workbook

Sheet Read Me
B2: FinTechCo — FP&A Junior Analyst Case Study
B4: Data Workbook — FY2025 (Jan–Dec), Budget vs. Actual
B6: Purpose: This workbook contains the historical financial and operating data referenced in the
B7: candidate case study packet. Use it to complete the Budget vs. Actual analysis, variance drivers,
B8: growth rates, 3-month forecast, and recommendation memo.
B10: Sheet guide:
B11: • Monthly Data (B vs A) — all Budget vs. Actual line items, Jan–Dec 2025, in $'000 unless noted.
B12: • KPI Data — Active Merchants, Transactions, and derived unit economics, Budget vs. Actual.
B13: • Candidate Workspace — a blank scaffold (variance %, MoM/YoY growth, 3-month forecast) for you
B14: to build your analysis directly in Excel. Formulas, not hardcoded numbers, are expected.
B16: Currency: All $ figures in USD thousands ($'000) unless a row label states otherwise.
B17: Fiscal year: Calendar year (Jan–Dec 2025). Prior-year (FY2024) comparatives are provided
... B22: for the purposes of this exercise, starting cash balance of $2,200K as of Jan 1, 2025).

Sheet Monthly Data
B1: Monthly Data — FY2025 Budget vs. Actual (Source: NoqtaPay Candidate Packet, Word doc)
B3: 1. Revenue ($'000)
B4: Metric | C4: Jan-25 | D4: Feb-25 | E4: Mar-25 | F4: Apr-25 | G4: May-25 | H4: Jun-25 | I4: Jul-25 | J4: Aug-25 | K4: Sep-25 | L4: Oct-25 | M4: Nov-25 | N4: Dec-25 | O4: FY Total/Avg
B5: Budget | C5: 480 | D5: 505 | E5: 530 | F5: 555 | G5: 570 | H5: 605 | I5: 640 | J5: 680 | K5: 720 | L5: 760 | M5: 800 | N5: 850 | O5: =SUM(C5:N5) -> 7695
B6: Actual | C6: 475 | D6: 495 | E6: 515 | F6: 530 | G6: 540 | H6: 555 | I6: 570 | J6: 580 | K6: 600 | L6: 615 | M6: 630 | N6: 650 | O6: =SUM(C6:N6) -> 6755
B7: LY '2024 | C7: 342 | D7: 356 | E7: 371 | F7: 382 | G7: 389 | H7: 400 | I7: 410 | J7: 418 | K7: 432 | L7: 443 | M7: 454 | N7: 468 | O7: =SUM(C7:N7) -> 4865
B9: 2. Gross Profit & Gross Margin
B10: Metric | C10: Jan-25 | D10: Feb-25 | E10: Mar-25 | F10: Apr-25 | G10: May-25 | H10: Jun-25 | I10: Jul-25 | J10: Aug-25 | K10: Sep-25 | L10: Oct-25 | M10: Nov-25 | N10: Dec-25 | O10: FY Total/Avg
B11: Gross Margin % - Budget | C11: 0.7 | D11: 0.7 | E11: 0.7 | F11: 0.7 | G11: 0.7 | H11: 0.7 | I11: 0.7 | J11: 0.7 | K11: 0.7 | L11: 0.7 | M11: 0.7 | N11: 0.7 | O11: =AVERAGE(C11:N11) -> 0.7
B12: Gross Margin % - Actual | C12: 0.7 | D12: 0.69 | E12: 0.68 | F12: 0.67 | G12: 0.66 | H12: 0.65 | I12: 0.64 | J12: 0.63 | K12: 0.62 | L12: 0.61 | M12: 0.6 | N12: 0.6 | O12: =AVERAGE(C12:N12) -> 0.64583333
B13: Gross Profit - Budget | C13: 336 | D13: 354 | E13: 371 | F13: 388 | G13: 399 | H13: 424 | I13: 448 | J13: 476 | K13: 504 | L13: 532 | M13: 560 | N13: 595 | O13: =SUM(C13:N13) -> 5387
B14: Gross Profit - Actual | C14: 332 | D14: 342 | E14: 350 | F14: 355 | G14: 356 | H14: 361 | I14: 365 | J14: 365 | K14: 372 | L14: 375 | M14: 378 | N14: 390 | O14: =SUM(C14:N14) -> 4341
B16: 3. Operating Expenses ($'000)
B17: Metric | C17: Jan-25 | D17: Feb-25 | E17: Mar-25 | F17: Apr-25 | G17: May-25 | H17: Jun-25 | I17: Jul-25 | J17: Aug-25 | K17: Sep-25 | L17: Oct-25 | M17: Nov-25 | N17: Dec-25 | O17: FY Total/Avg
B18: Salaries & Benefits - Budget | C18: 215 | D18: 220 | E18: 225 | F18: 232 | G18: 238 | H18: 245 | I18: 250 | J18: 258 | K18: 263 | L18: 270 | M18: 276 | N18: 282 | O18: =SUM(C18:N18) -> 2974
B19: Salaries & Benefits - Actual | C19: 222 | D19: 232 | E19: 244 | F19: 258 | G19: 268 | H19: 282 | I19: 292 | J19: 302 | K19: 308 | L19: 314 | M19: 320 | N19: 320 | O19: =SUM(C19:N19) -> 3362
B20: Marketing - Budget | C20: 70 | D20: 74 | E20: 78 | F20: 82 | G20: 85 | H20: 90 | I20: 95 | J20: 100 | K20: 105 | L20: 110 | M20: 115 | N20: 120 | O20: =SUM(C20:N20) -> 1124
B21: Marketing - Actual | C21: 72 | D21: 80 | E21: 90 | F21: 100 | G21: 110 | H21: 125 | I21: 140 | J21: 155 | K21: 165 | L21: 175 | M21: 180 | N21: 185 | O21: =SUM(C21:N21) -> 1577
B22: Software & Tools - Budget | C22: 18 | D22: 18 | E22: 19 | F22: 19 | G22: 20 | H22: 20 | I22: 21 | J22: 21 | K22: 22 | L22: 22 | M22: 23 | N22: 23 | O22: =SUM(C22:N22) -> 246
B23: Software & Tools - Actual | C23: 18 | D23: 19 | E23: 20 | F23: 21 | G23: 22 | H23: 23 | I23: 24 | J23: 25 | K23: 26 | L23: 27 | M23: 28 | N23: 29 | O23: =SUM(C23:N23) -> 282
B24: G&A - Budget | C24: 35 | D24: 35 | E24: 36 | F24: 36 | G24: 37 | H24: 37 | I24: 38 | J24: 38 | K24: 39 | L24: 39 | M24: 40 | N24: 40 | O24: =SUM(C24:N24) -> 450
B25: G&A - Actual | C25: 36 | D25: 37 | E25: 38 | F25: 39 | G25: 40 | H25: 42 | I25: 43 | J25: 45 | K25: 46 | L25: 48 | M25: 49 | N25: 50 | O25: =SUM(C25:N25) -> 513
B26: Total OpEx - Budget | C26: =C18+C20+C22+C24 -> 338 | D26: =D18+D20+D22+D24 -> 347 | E26: =E18+E20+E22+E24 -> 358 | F26: =F18+F20+F22+F24 -> 369 | G26: =G18+G20+G22+G24 -> 380 | H26: =H18+H20+H22+H24 -> 392 | I26: =I18+I20+I22+I24 -> 404 | J26: =J18+J20+J22+J24 -> 417 | ... N26: =N18+N20+N22+N24 -> 465 | O26: =SUM(C26:N26) -> 4794
B27: Total OpEx - Actual | C27: =C19+C21+C23+C25 -> 348 | D27: =D19+D21+D23+D25 -> 368 | E27: =E19+E21+E23+E25 -> 392 | F27: =F19+F21+F23+F25 -> 418 | G27: =G19+G21+G23+G25 -> 440 | H27: =H19+H21+H23+H25 -> 472 | I27: =I19+I21+I23+I25 -> 499 | J27: =J19+J21+J23+J25 -> 527 | ... N27: =N19+N21+N23+N25 -> 584 | O27: =SUM(C27:N27) -> 5734
B29: 4. EBITDA ($'000)
B30: Metric | C30: Jan-25 | D30: Feb-25 | E30: Mar-25 | F30: Apr-25 | G30: May-25 | H30: Jun-25 | I30: Jul-25 | J30: Aug-25 | K30: Sep-25 | L30: Oct-25 | M30: Nov-25 | N30: Dec-25 | O30: FY Total/Avg
B31: Budget | C31: =C13-C26 -> -2 | D31: =D13-D26 -> 7 | E31: =E13-E26 -> 13 | F31: =F13-F26 -> 19 | G31: =G13-G26 -> 19 | H31: =H13-H26 -> 32 | I31: =I13-I26 -> 44 | J31: =J13-J26 -> 59 | ... N31: =N13-N26 -> 130 | O31: =SUM(C31:N31) -> 593
B32: Actual | C32: =C14-C27 -> -16 | D32: =D14-D27 -> -26 | E32: =E14-E27 -> -42 | F32: =F14-F27 -> -63 | G32: =G14-G27 -> -84 | H32: =H14-H27 -> -111 | I32: =I14-I27 -> -134 | J32: =J14-J27 -> -162 | ... N32: =N14-N27 -> -194 | O32: =SUM(C32:N32) -> -1393
B34: 5. Cash Balance ($'000, EOM) & Headcount
B35: Metric | C35: Jan-25 | D35: Feb-25 | E35: Mar-25 | F35: Apr-25 | G35: May-25 | H35: Jun-25 | I35: Jul-25 | J35: Aug-25 | K35: Sep-25 | L35: Oct-25 | M35: Nov-25 | N35: Dec-25 | O35: FY Total/Avg
B36: Cash - Budget | C36: 2198 | D36: 2204 | E36: 2218 | F36: 2237 | G36: 2256 | H36: 2288 | I36: 2332 | J36: 2390 | K36: 2466 | L36: 2556 | M36: 2662 | N36: 2792 | O36: =SUM(C36:N36) -> 28599
B37: Cash - Actual | C37: 2184 | D37: 2158 | E37: 2116 | F37: 2053 | G37: 1970 | H37: 1858 | I37: 1724 | J37: 1563 | K37: 1390 | L37: 1201 | M37: 1002 | N37: 808 | O37: =SUM(C37:N37) -> 20027
B38: Headcount - Budget | C38: 40 | D38: 41 | E38: 42 | F38: 44 | G38: 45 | H38: 47 | I38: 48 | J38: 50 | K38: 51 | L38: 53 | M38: 54 | N38: 55 | O38: =AVERAGE(C38:N38) -> 47.5
B39: Headcount - Actual | C39: 42 | D39: 44 | E39: 47 | F39: 50 | G39: 52 | H39: 55 | I39: 57 | J39: 59 | K39: 60 | L39: 61 | M39: 62 | N39: 62 | O39: =AVERAGE(C39:N39) -> 54.25
B41: 6. Active Merchants & Transactions ('000)
B42: Metric | C42: Jan-25 | D42: Feb-25 | E42: Mar-25 | F42: Apr-25 | G42: May-25 | H42: Jun-25 | I42: Jul-25 | J42: Aug-25 | K42: Sep-25 | L42: Oct-25 | M42: Nov-25 | N42: Dec-25 | O42: FY Total/Avg
B43: Active Merchants - Budget | C43: 1200 | D43: 1260 | E43: 1320 | F43: 1380 | G43: 1440 | H43: 1520 | I43: 1600 | J43: 1680 | K43: 1760 | L43: 1840 | M43: 1920 | N43: 2000 | O43: =AVERAGE(C43:N43) -> 1576.6667
B44: Active Merchants - Actual | C44: 1180 | D44: 1230 | E44: 1270 | F44: 1310 | G44: 1340 | H44: 1370 | I44: 1390 | J44: 1410 | K44: 1430 | L44: 1450 | M44: 1470 | N44: 1490 | O44: =AVERAGE(C44:N44) -> 1361.6667
B45: Transactions, '000 - Budget | C45: 340 | D45: 358 | E45: 376 | F45: 394 | G45: 412 | H45: 437 | I45: 462 | J45: 487 | K45: 512 | L45: 537 | M45: 562 | N45: 587 | O45: =SUM(C45:N45) -> 5464
B46: Transactions, '000 - Actual | C46: 335 | D46: 350 | E46: 362 | F46: 372 | G46: 380 | H46: 388 | I46: 394 | J46: 400 | K46: 408 | L46: 415 | M46: 422 | N46: 428 | O46: =SUM(C46:N46) -> 4654

Sheet Section 1
B2: Section 1: Budget vs. Actual Analysis — Full-Year Summary
B3: Metric | C3: Actual | D3: Budget | E3: Variance ($) | F3: Variance (%)
B4: Revenue | C4: ='Monthly Data'!O6 -> 6755 | D4: ='Monthly Data'!O5 -> 7695 | E4: =C4-D4 -> -940 | F4: =E4/D4 -> -0.12215724
B5: Gross Profit ($'000) | C5: ='Monthly Data'!O14 -> 4341 | D5: ='Monthly Data'!O13 -> 5387 | E5: =C5-D5 -> -1046 | F5: =E5/D5 -> -0.19417115
B6: Total OpEx ($'000) | C6: ='Monthly Data'!O27 -> 5734 | D6: ='Monthly Data'!O26 -> 4794 | E6: =C6-D6 -> 940 | F6: =E6/D6 -> 0.19607843
B7: EBITDA ($'000) | C7: ='Monthly Data'!O32 -> -1393 | D7: ='Monthly Data'!O31 -> 593 | E7: =C7-D7 -> -1986 | F7: =E7/D7 -> -3.3490725
B8: Cash Balance, EOM ($'000) | C8: ='Monthly Data'!N37 -> 808 | D8: ='Monthly Data'!N36 -> 2792 | E8: =C8-D8 -> -1984 | F8: =E8/D8 -> -0.71060172
B9: Headcount, EOM | C9: ='Monthly Data'!N39 -> 62 | D9: ='Monthly Data'!N38 -> 55 | E9: =C9-D9 -> 7 | F9: =E9/D9 -> 0.12727273
B10: Note: Cash Balance & Headcount are December (EOM) values, not annual totals — all other rows are FY totals.
B11: Key observations expected from candidates:
B12: Assumption 1: Revenue came in 12% below budget, mainly due to slower merchant onboarding and stronger competition.
B13: Assumption 2: Gross Margin dropped from 70% to 60% because BNPL (which costs more) became a bigger share of revenue.
B14: Assumption 3: Marketing spend grew much faster than revenue, but it didn't bring in more merchants than planned.
B15: Assumption 4: Headcount grew ahead of plan (62 vs. 55), adding cost pressure on top of the revenue miss.
B16: Assumption 5: Cash is burning faster than budgeted, which puts pressure on runway before the Series B round.

Sheet Section 2
B2: Section 2: Variance Driver Analysis — EBITDA Bridge
B3: Bridge Item | C3: Amount ($'000)
B4: Full-Year EBITDA - Budget | C4: ='Monthly Data'!O31 -> 593
B5: Revenue Shortfall Impact | C5: =('Monthly Data'!O6-'Monthly Data'!O5)*'Monthly Data'!O11 -> -658
B6: Gross Margin Compression Impact | C6: =('Monthly Data'!O14-'Monthly Data'!O13)-C5 -> -388
B7: Marketing Overspend Impact | C7: =-('Monthly Data'!O21-'Monthly Data'!O20) -> -453
B8: Salary/Headcount Overspend Impact | C8: =-('Monthly Data'!O19-'Monthly Data'!O18) -> -388
B9: Software Overspend Impact | C9: =-('Monthly Data'!O23-'Monthly Data'!O22) -> -36
B10: G&A Overspend Impact | C10: =-('Monthly Data'!O25-'Monthly Data'!O24) -> -63
B11: Full-Year EBITDA - Actual (should tie out) | C11: =SUM(C4:C10) -> -1393
B12: Rounding | C12: =C11-'Section 1'!C7 -> 0
B13: Key observations expected from candidates:
B14: Assumption 1: Revenue drop was the biggest driver of the loss (-$658k).
B15: Assumption 2: Margin decline was the second biggest driver (-$388K).
B16: Assumption 3: Marketing overspend was the largest cost problem (-$453K), with little payoff in new merchants.
B17: Assumption 4: Salary overspend (-$388K) came from hiring faster than planned.
B18: Assumption 5: Revenue and margin issues together explain over half the total gap - bigger than all the cost overruns combined.

Sheet Section 3
B2: Section 3: Revenue Variance & Growth Rates
B3: Metric | C3: Jan-25 | D3: Feb-25 | E3: Mar-25 | F3: Apr-25 | G3: May-25 | H3: Jun-25 | I3: Jul-25 | J3: Aug-25 | K3: Sep-25 | L3: Oct-25 | M3: Nov-25 | N3: Dec-25
B4: Revenue - Budget ($'000) | C4: ='Monthly Data'!C5 -> 480 | D4: ='Monthly Data'!D5 -> 505 | E4: ='Monthly Data'!E5 -> 530 | F4: ='Monthly Data'!F5 -> 555 | G4: ='Monthly Data'!G5 -> 570 | H4: ='Monthly Data'!H5 -> 605 | I4: ='Monthly Data'!I5 -> 640 | J4: ='Monthly Data'!J5 -> 680 | ... N4: ='Monthly Data'!N5 -> 850
B5: Revenue - Actual ($'000) | C5: ='Monthly Data'!C6 -> 475 | D5: ='Monthly Data'!D6 -> 495 | E5: ='Monthly Data'!E6 -> 515 | F5: ='Monthly Data'!F6 -> 530 | G5: ='Monthly Data'!G6 -> 540 | H5: ='Monthly Data'!H6 -> 555 | I5: ='Monthly Data'!I6 -> 570 | J5: ='Monthly Data'!J6 -> 580 | ... N5: ='Monthly Data'!N6 -> 650
B6: Revenue - LY'2024 ($'000) | C6: ='Monthly Data'!C7 -> 342 | D6: ='Monthly Data'!D7 -> 356 | E6: ='Monthly Data'!E7 -> 371 | F6: ='Monthly Data'!F7 -> 382 | G6: ='Monthly Data'!G7 -> 389 | H6: ='Monthly Data'!H7 -> 400 | I6: ='Monthly Data'!I7 -> 410 | J6: ='Monthly Data'!J7 -> 418 | ... N6: ='Monthly Data'!N7 -> 468
B7: $ Variance (Actual - Budget) | C7: =C5-C4 -> -5 | D7: =D5-D4 -> -10 | E7: =E5-E4 -> -15 | F7: =F5-F4 -> -25 | G7: =G5-G4 -> -30 | H7: =H5-H4 -> -50 | I7: =I5-I4 -> -70 | J7: =J5-J4 -> -100 | ... N7: =N5-N4 -> -200
B8: % Variance (Actual vs Budget) | C8: =C7/C4 -> -0.010416667 | D8: =D7/D4 -> -0.01980198 | E8: =E7/E4 -> -0.028301887 | F8: =F7/F4 -> -0.045045045 | G8: =G7/G4 -> -0.052631579 | H8: =H7/H4 -> -0.082644628 | I8: =I7/I4 -> -0.109375 | J8: =J7/J4 -> -0.14705882 | ... N8: =N7/N4 -> -0.23529412
B9: MoM Growth % (Actual) | D9: =(D5-C5)/C5 -> 0.042105263 | E9: =(E5-D5)/D5 -> 0.04040404 | F9: =(F5-E5)/E5 -> 0.029126214 | G9: =(G5-F5)/F5 -> 0.018867925 | H9: =(H5-G5)/G5 -> 0.027777778 | I9: =(I5-H5)/H5 -> 0.027027027 | J9: =(J5-I5)/I5 -> 0.01754386 | K9: =(K5-J5)/J5 -> 0.034482759 | ... N9: =(N5-M5)/M5 -> 0.031746032
B10: YoY Growth % (Actual vs FY24) | C10: =(C5-C6)/C6 -> 0.38888889 | D10: =(D5-D6)/D6 -> 0.39044944 | E10: =(E5-E6)/E6 -> 0.38814016 | F10: =(F5-F6)/F6 -> 0.38743455 | G10: =(G5-G6)/G6 -> 0.38817481 | H10: =(H5-H6)/H6 -> 0.3875 | I10: =(I5-I6)/I6 -> 0.3902439 | J10: =(J5-J6)/J6 -> 0.38755981 | ... N10: =(N5-N6)/N6 -> 0.38888889
B12: Key observations expected from candidates:
B13: Assumption 1: The gap between actual and budget grew every month -> from -1% in January to -23.5% by December.
B14: Assumption 2: MoM growth was strongest in February and weakest in August, showing momentum faded through the year rather than staying steady.
B15: Assumption 3: YoY growth looks strong and steady at 38.9% but this hides the bigger issue: the budget expected even faster growth, which is why the gap kept widening despite real growth happening.
B16: Assumption 4: The slowdown timing lines up with the Q2 product launch and Q3 competitor pricing mentioned in the scenario.
B17: Assumption 5: This is a worsening trend against budget, not against last year -YoY growth looks healthy, but the budget gap points to a real, growing execution problem that needs fixing.
F31: }

Sheet Section 4
B2: Section 4: 3-Month Forecast (Jan–Mar 2026)
B3: Metric | C3: Dec-25 | D3: Jan-26 | E3: Feb-26 | F3: Mar-26
B4: Revenue ($'000) | C4: ='Monthly Data'!N6 -> 650 | D4: =C4*1.025 -> 666.25 | E4: =1.025*D4 -> 682.90625 | F4: =1.025*E4 -> 699.97891
B5: Gross Margin % (assumption) | C5: ='Monthly Data'!N12 -> 0.6 | D5: =C5 -> 0.6 | E5: =D5 -> 0.6 | F5: =E5 -> 0.6
B6: Gross Profit ($'000) | D6: =D4*D5 -> 399.75 | E6: =E4*E5 -> 409.74375 | F6: =F4*F5 -> 419.98734
B7: Salaries ($'000) | C7: ='Monthly Data'!N19 -> 320 | D7: =C7*1.01 -> 323.2 | E7: =D7*1.01 -> 326.432 | F7: =E7*1.01 -> 329.69632
B8: Marketing ($'000) | D8: =D4*D9 -> 168.78333 | E8: =E4*E9 -> 154.79208 | F8: =F4*F9 -> 139.99578
B9: Marketing % of Revenue (assumption) | C9: 0.28 | D9: =C9-(28%-20%)/3 -> 0.25333333 | E9: =D9-(28%-20%)/3 -> 0.22666667 | F9: =E9-(28%-20%)/3 -> 0.2
B10: Software ($'000) | C10: ='Monthly Data'!N23 -> 29 | D10: =C10*1.026 -> 29.754 | E10: =D10*1.026 -> 30.527604 | F10: =E10*1.026 -> 31.321322
B11: G&A ($'000) | C11: ='Monthly Data'!N25 -> 50 | D11: =C11*1.026 -> 51.3 | E11: =D11*1.026 -> 52.6338 | F11: =E11*1.026 -> 54.002279
B12: Total OpEx ($'000) | D12: =SUM(D7:D8:D10:D11) -> 573.29067 | E12: =SUM(E7:E8:E10:E11) -> 564.61215 | F12: =SUM(F7:F8:F10:F11) -> 555.2157
B13: EBITDA ($'000) | D13: =D6-D12 -> -173.54067 | E13: =E6-E12 -> -154.8684 | F13: =F6-F12 -> -135.22836

Sheet Section 5&6
B2: Section 5: Cost Optimization Recommendations For Marketing
B3: Recommendation | C3: Estimated Annualized Impact
B4: 1- Cut spend on underperforming marketing channels that grew fastest in 2025 without a proportional increase in new merchants. | C4: 150000
B5: Follow through on the planned reduction of Marketing % of Revenue from 28% to 20% by end of Q1 2026, and hold it there. | C5: 180000
B6: Set a maximum Customer Acquisition Cost (CAC) per channel and reallocate budget only to channels below that cap. | C6: 100000
B9: Section 6: Annual EBITDA Target Assessment
B11: FinTechCo is improving but still hasn't reached EBITDA breakeven by March 2026 (-$135K). If this pace continues (~$19K improvement per month), breakeven should arrive around Q4 2026. But this only holds if costs stay controlled — extra hiring beyond the Q1 plan or rising marketing spend could stall this progress and push breakeven into 2027 or later

Sheet Bonus Questions
B2: Bonus Questions: Cash Runway Assessment
B5: Metric | C5: Value | D5: Note
B6: Cash Balance, EOM (Dec-25) | C6: ='Monthly Data'!N37 -> 808
B7: Average Monthly Cash Burn (Oct-Dec) | C7: =AVERAGE('Monthly Data'!K37-'Monthly Data'!L37,'Monthly Data'!L37-'Monthly Data'!M37, 'Monthly Data'!M37-'Monthly Data'!N37) -> 194
B8: Cash Runway (Months) | C8: =C6/C7 -> 4.1649485
B9: Board Minimum Runway Target (Months) | C9: 12
B10: Recommend whether FinTechCo should draw on the $1,500K credit facility and under what circumstances.
B12: With only 4.2 months of runway against the Board's 12-month target, FinTechCo should draw part of the $1,500K credit facility now as a precaution -- enough to extend runway to a safer level — rather than wait and risk running out of cash. At the same time, the company should move quickly on the Marketing and headcount cost cuts from Section 5, so future draws become less likely.
